webrtc_noise_gain_cpp.cpython-39-aarch64-linux-gnu.so
webrtc_noise_gain-1.2.5.dist-info/RECORD
webrtc_noise_gain-1.2.5.dist-info/top_level.txt
webrtc_noise_gain-1.2.5.dist-info/WHEEL
webrtc_noise_gain-1.2.5.dist-info/METADATA
webrtc_noise_gain/__init__.py
