Metadata-Version: 2.1
Name: webrtc_noise_gain
Version: 1.2.5
Summary: Noise suppression and automatic gain with webrtc
Home-page: https://github.com/rhasspy/webrtc-noise-gain
Author: Michael Hansen
Author-email: mike@rhasspy.org
Classifier: License :: OSI Approved :: MIT License
Requires-Python: >=3.7
License-File: LICENSE.md
